pyansys_sphinx_theme/__init__.py
pyansys_sphinx_theme/breadcrumbs.html
pyansys_sphinx_theme/docs-navbar.html
pyansys_sphinx_theme/icon-links.html
pyansys_sphinx_theme/layout.html
pyansys_sphinx_theme/sample_func.py
pyansys_sphinx_theme/samples.py
pyansys_sphinx_theme/theme.conf
pyansys_sphinx_theme/_templates/autosummary/base.rst
pyansys_sphinx_theme/_templates/autosummary/class.rst
pyansys_sphinx_theme/latex/__init__.py
pyansys_sphinx_theme/latex/cover.tex
pyansys_sphinx_theme/static/ansys-favicon.png
pyansys_sphinx_theme/static/ansys_logo_white.pdf
pyansys_sphinx_theme/static/ansys_logo_white_cropped.pdf
pyansys_sphinx_theme/static/pyansys-logo-black-cropped.png
pyansys_sphinx_theme/static/pyansys-logo-white-cropped.png
pyansys_sphinx_theme/static/pyansys_dark.png
pyansys_sphinx_theme/static/pyansys_dark_square.png
pyansys_sphinx_theme/static/pyansys_light.png
pyansys_sphinx_theme/static/pyansys_light_square.png
pyansys_sphinx_theme/static/watermark.pdf
pyansys_sphinx_theme/static/css/breadcrumbs.css
pyansys_sphinx_theme/static/css/pyansys_sphinx_theme.css
pyansys_sphinx_theme/static/fonts/SourceSansPro-Light.ttf
pyansys_sphinx_theme/static/fonts/SourceSansPro-Regular.ttf
pyansys_sphinx_theme/static/fonts/SourceSansPro-SemiBold.ttf
pyansys_sphinx_theme/static/js/download_target_blank.js
pyansys_sphinx_theme-0.3.1.dist-info/entry_points.txt
pyansys_sphinx_theme-0.3.1.dist-info/LICENSE
pyansys_sphinx_theme-0.3.1.dist-info/WHEEL
pyansys_sphinx_theme-0.3.1.dist-info/METADATA
pyansys_sphinx_theme-0.3.1.dist-info/RECORD
