Metadata-Version: 2.1
Name: pyansys-sphinx-theme
Version: 0.3.1
Summary: This is the pyansys-sphinx-theme module.
Author-email: "ANSYS, Inc." <pyansys.support@ansys.com>
Maintainer-email: PyAnsys developers <pyansys.maintainers@ansys.com>
Requires-Python: >=3.5
Classifier: Development Status :: 4 - Beta
Classifier: Framework :: Sphinx
Classifier: Framework :: Sphinx :: Theme
Classifier: License :: OSI Approved :: MIT License
Classifier: Operating System :: OS Independent
Classifier: Programming Language :: Python :: 3
Requires-Dist: Sphinx>=4.0.0
Requires-Dist: pydata-sphinx-theme==0.8.1
Requires-Dist: Jinja2>=3.1.2
Project-URL: Home, https://docs.pyansys.com/
Project-URL: Source, https://github.com/pyansys/pyansys-sphinx-theme
Project-URL: Tracker, https://github.com/pyansys/pyansys-sphinx-theme/issues
